tdmagsus/__init__.py
tdmagsus/tdmagsus.py
tdmagsus-1.0.2.dist-info/COPYING
tdmagsus-1.0.2.dist-info/METADATA
tdmagsus-1.0.2.dist-info/WHEEL
tdmagsus-1.0.2.dist-info/top_level.txt
tdmagsus-1.0.2.dist-info/RECORD
