Metadata-Version: 2.1
Name: tdmagsus
Version: 1.0.2
Summary: Manipulation of temperature-dependent magnetic susceptibility data
Home-page: https://github.com/pont-us/tdmagsus
Author: Pontus Lurcock
Author-email: pont@talvi.net
License: GNU GPLv3+
Platform: UNKNOWN
Classifier: Development Status :: 5 - Production/Stable
Classifier: License :: OSI Approved :: GNU General Public License v3 or later (GPLv3+)
Classifier: Topic :: Scientific/Engineering
Classifier: Programming Language :: Python :: 3
Classifier: Intended Audience :: Science/Research
Requires-Dist: numpy
Requires-Dist: scipy
